biomapper/__init__.py
biomapper/core/__init__.py
biomapper/core/base_client.py
biomapper/core/base_llm.py
biomapper/core/base_mapper.py
biomapper/core/base_pipeline.py
biomapper/core/base_rag.py
biomapper/core/base_spoke.py
biomapper/core/base_store.py
biomapper/core/protein_metadata_comparison.py
biomapper/core/set_analysis.py
biomapper/llm/__init__.py
biomapper/llm/analyzer.py
biomapper/llm/prompts.py
biomapper/loaders/__init__.py
biomapper/loaders/hmdb_loader.py
biomapper/mapping/__init__.py
biomapper/mapping/arango/arango_store.py
biomapper/mapping/arango/base_arango.py
biomapper/mapping/clients/__init__.py
biomapper/mapping/clients/chebi_client.py
biomapper/mapping/clients/metaboanalyst_client.py
biomapper/mapping/clients/refmet_client.py
biomapper/mapping/clients/unichem_client.py
biomapper/mapping/clients/uniprot_focused_mapper.py
biomapper/mapping/embeddings/__init__.py
biomapper/mapping/embeddings/managers.py
biomapper/mapping/rag/__init__.py
biomapper/mapping/rag/base_rag.py
biomapper/mapping/rag/chroma.py
biomapper/mapping/rag/compound_mapper.py
biomapper/mapping/rag/data/default_prompts.json.template
biomapper/mapping/rag/embedder.py
biomapper/mapping/rag/prompts.py
biomapper/mapping/rag/store.py
biomapper/mapping/result_processor.py
biomapper/monitoring/langfuse_tracker.py
biomapper/monitoring/metrics.py
biomapper/monitoring/traces.py
biomapper/pipelines/compounds/__init__.py
biomapper/pipelines/compounds/compound_mapper.py
biomapper/pipelines/compounds/compound_pipeline.py
biomapper/pipelines/compounds/rag_compound_mapper.py
biomapper/pipelines/proteins/__init__.py
biomapper/pipelines/proteins/protein_mapper.py
biomapper/pipelines/proteins/protein_pipeline.py
biomapper/processors/__init__.py
biomapper/processors/base.py
biomapper/processors/hmdb.py
biomapper/py.typed
biomapper/schemas/__init__.py
biomapper/schemas/domain_schema.py
biomapper/schemas/llm_schema.py
biomapper/schemas/metabolite_schema.py
biomapper/schemas/provider_schemas.py
biomapper-0.5.2.dist-info/LICENSE
biomapper-0.5.2.dist-info/METADATA
biomapper-0.5.2.dist-info/WHEEL
biomapper-0.5.2.dist-info/entry_points.txt
biomapper-0.5.2.dist-info/RECORD
