Metadata-Version: 2.3
Name: biomapper
Version: 0.5.2
Summary: A unified Python toolkit for biological data harmonization and ontology mapping
License: MIT
Keywords: bioinformatics,ontology,data mapping,biological data,standardization,harmonization
Author: Trent Leslie
Author-email: trent.leslie@phenomehealth.org
Requires-Python: >=3.11,<4.0
Classifier: Development Status :: 3 - Alpha
Classifier: Intended Audience :: Science/Research
Classifier: License :: OSI Approved :: MIT License
Classifier: Natural Language :: English
Classifier: Operating System :: OS Independent
Classifier: Programming Language :: Python :: 3
Classifier: Programming Language :: Python :: 3.11
Classifier: Programming Language :: Python :: 3.12
Classifier: Programming Language :: Python :: 3.13
Classifier: Topic :: Scientific/Engineering :: Bio-Informatics
Provides-Extra: api
Provides-Extra: full
Requires-Dist: aiohttp (>=3.11.11,<4.0.0)
Requires-Dist: chromadb (>=0.6.2,<0.7.0)
Requires-Dist: cloudpickle (>=3.0.0,<4.0.0)
Requires-Dist: cryptography (>=43.0.1)
Requires-Dist: dspy-ai (>=2.1.8,<3.0.0)
Requires-Dist: faiss-cpu (>=1.10.0,<2.0.0)
Requires-Dist: fastembed (>=0.5.1,<0.6.0)
Requires-Dist: langfuse (>=2.57.1,<3.0.0)
Requires-Dist: libChEBIpy (==1.0.10)
Requires-Dist: lxml (>=5.3.1,<6.0.0)
Requires-Dist: matplotlib (>=3.8.0,<4.0.0)
Requires-Dist: numpy (>=2.1.0)
Requires-Dist: openai (>=1.14.0,<2.0.0)
Requires-Dist: pandas (>=2.0.0,<3.0.0)
Requires-Dist: pyarango (>=2.1.1,<3.0.0)
Requires-Dist: python-dotenv (>=1.0.1,<2.0.0)
Requires-Dist: python-multipart (>=0.0.10,<0.0.11)
Requires-Dist: pyyaml (>=6.0.1,<7.0.0)
Requires-Dist: rdkit (>=2023.9.1,<2024.0.0)
Requires-Dist: requests (>=2.25.1,<3.0.0)
Requires-Dist: seaborn (>=0.13.0,<0.14.0)
Requires-Dist: sentence-transformers (>=2.2.2,<3.0.0)
Requires-Dist: sqlalchemy (>=1.4.0,<2.0.0)
Requires-Dist: torch (>=2.2.0,<3.0.0)
Requires-Dist: tqdm (>=4.66.1,<5.0.0)
Requires-Dist: transformers (>=4.38.2,<5.0.0)
Requires-Dist: upsetplot (>=0.8.0,<0.9.0)
Requires-Dist: venn (>=0.1.3,<0.2.0)
Project-URL: Documentation, https://biomapper.readthedocs.io/
Project-URL: Repository, https://github.com/arpanauts/biomapper
